README.md
setup.cfg
setup.py
lemons/__init__.py
lemons/analysis.py
lemons/gui.py
lemons.egg-info/PKG-INFO
lemons.egg-info/SOURCES.txt
lemons.egg-info/dependency_links.txt
lemons.egg-info/top_level.txt