Metadata-Version: 2.1
Name: lemons
Version: 0.22
Summary: A GUI-building and data-crunching utility package.
Home-page: https://github.com/jakebrehm/lemons
Author: Jake Brehm
Author-email: mail@jakebrehm.com
License: MIT
Platform: UNKNOWN
Classifier: Programming Language :: Python :: 3.7
Classifier: Operating System :: OS Independent
